live_apis/main_api/__init__.py
live_apis/main_api/api.py
live_apis/registry/__init__.py
live_apis/registry/registry.py
live_apis/registry/update_cpyver.py
live_apis/registry/update_packsver.py
caplit_cl_nt-1.0.dist-info/LICENSE
caplit_cl_nt-1.0.dist-info/METADATA
caplit_cl_nt-1.0.dist-info/WHEEL
caplit_cl_nt-1.0.dist-info/top_level.txt
caplit_cl_nt-1.0.dist-info/RECORD
