Metadata-Version: 2.1
Name: caplit-cl-nt
Version: 1.0
Summary: CoreApps Cross-Platform Compatibility Layer For Windows 10 or Later
Author-email: PieTech Workspace <ptstudio@tlyhb.onmicrosoft.com>
License: GNU LESSER GENERAL PUBLIC LICENSE
Project-URL: Homepage, https://gitee.com/yizhigezi_yijiafeiji/coreapps-compatibility-layer/tree/master
Project-URL: Bug Tracker, https://gitee.com/yizhigezi_yijiafeiji/coreapps-compatibility-layer/issues
Classifier: Programming Language :: Python :: 3.10
Classifier: License :: OSI Approved :: GNU Lesser General Public License v2 or later (LGPLv2+)
Classifier: Operating System :: Microsoft :: Windows
Requires-Python: >=3.10
License-File: LICENSE
